{
  "id": "Briar",
  "name": "Briar",
  "positions": [
    "Jungle"
  ],
  "matchups": {
    "top": {
      "Sylas": 72.22,
      "Wukong": 68.42,
      "Shen": 66.67,
      "Teemo": 63.89,
      "Quinn": 61.11,
      "Camille": 60.47,
      "Jax": 60,
      "Singed": 60,
      "Urgot": 59.09,
      "Nasus": 58.82,
      "Riven": 58.73,
      "Pantheon": 58.33,
      "Illaoi": 58.33,
      "Ambessa": 57.58,
      "Sett": 55.88,
      "Yasuo": 55.36,
      "Malphite": 55.06,
      "Tryndamere": 54.9,
      "Garen": 54.85,
      "Olaf": 54.29,
      "Vladimir": 53.33,
      "Gangplank": 53.12,
      "Kled": 53.12,
      "Vayne": 53.06,
      "Yorick": 52.94,
      "Volibear": 52.94,
      "Yone": 52.78,
      "Trundle": 52,
      "Tahm Kench": 51.61,
      "Gragas": 51.61,
      "Irelia": 51.47,
      "Gnar": 51.39,
      "Kennen": 51.35,
      "Darius": 51.04,
      "Fiora": 50.77,
      "Aatrox": 50,
      "Ornn": 50,
      "Renekton": 50,
      "Cho'Gath": 48.72,
      "Zaahen": 48.15,
      "K'Sante": 48.15,
      "Varus": 48.15,
      "Heimerdinger": 47.37,
      "Mordekaiser": 47.25,
      "Udyr": 47.06,
      "Sion": 46.91,
      "Gwen": 46.34,
      "Jayce": 43.04,
      "Kayle": 43.04,
      "Rumble": 38.46,
      "Shyvana": 37.5,
      "Dr. Mundo": 37.04,
      "Akali": 36.96
    },
    "jungle": {
      "Amumu": 54.26,
      "Aatrox": 54.08,
      "Fizz": 54.03,
      "Darius": 52.82,
      "Master Yi": 51.66,
      "Rek'Sai": 51.63,
      "Nasus": 51.43,
      "Rammus": 51.42,
      "Warwick": 51.12,
      "Nocturne": 51,
      "Sejuani": 50.92,
      "Gwen": 50.9,
      "Bel'Veth": 50.87,
      "Shen": 50.65,
      "Naafiri": 50.63,
      "Graves": 50.55,
      "Hecarim": 50.54,
      "Zaahen": 50.42,
      "Udyr": 50.1,
      "Nidalee": 49.81,
      "Karthus": 49.77,
      "Elise": 49.69,
      "Shaco": 49.51,
      "Zac": 49.43,
      "Kayn": 49.43,
      "Fiddlesticks": 49.36,
      "Jax": 49.3,
      "Lillia": 49.23,
      "Evelynn": 49.1,
      "Xin Zhao": 49.02,
      "Shyvana": 48.96,
      "Ekko": 48.95,
      "Ivern": 48.77,
      "Dr. Mundo": 48.55,
      "Willump": 48.4,
      "Zyra": 48.17,
      "Volibear": 48.12,
      "Kha'Zix": 48.03,
      "Kindred": 47.99,
      "Diana": 47.71,
      "Viego": 47.65,
      "Jarvan IV": 47.31,
      "Wukong": 47.3,
      "Malphite": 47.26,
      "Talon": 47.23,
      "Lee Sin": 47.14,
      "Ambessa": 46.43,
      "Vi": 46.22,
      "Pantheon": 46.04,
      "Zed": 44.25,
      "Sylas": 44.03,
      "Rengar": 43.77
    },
    "middle": {
      "Amumu": 54.26,
      "Aatrox": 54.08,
      "Fizz": 54.03,
      "Darius": 52.82,
      "Master Yi": 51.66,
      "Rek'Sai": 51.63,
      "Nasus": 51.43,
      "Rammus": 51.42,
      "Warwick": 51.12,
      "Nocturne": 51,
      "Sejuani": 50.92,
      "Gwen": 50.9,
      "Bel'Veth": 50.87,
      "Shen": 50.65,
      "Naafiri": 50.63,
      "Graves": 50.55,
      "Hecarim": 50.54,
      "Zaahen": 50.42,
      "Udyr": 50.1,
      "Nidalee": 49.81,
      "Karthus": 49.77,
      "Elise": 49.69,
      "Shaco": 49.51,
      "Zac": 49.43,
      "Kayn": 49.43,
      "Fiddlesticks": 49.36,
      "Jax": 49.3,
      "Lillia": 49.23,
      "Evelynn": 49.1,
      "Xin Zhao": 49.02,
      "Shyvana": 48.96,
      "Ekko": 48.95,
      "Ivern": 48.77,
      "Dr. Mundo": 48.55,
      "Willump": 48.4,
      "Zyra": 48.17,
      "Volibear": 48.12,
      "Kha'Zix": 48.03,
      "Kindred": 47.99,
      "Diana": 47.71,
      "Viego": 47.65,
      "Jarvan IV": 47.31,
      "Wukong": 47.3,
      "Malphite": 47.26,
      "Talon": 47.23,
      "Lee Sin": 47.14,
      "Ambessa": 46.43,
      "Vi": 46.22,
      "Pantheon": 46.04,
      "Zed": 44.25,
      "Sylas": 44.03,
      "Rengar": 43.77
    },
    "adc": {
      "Zeri": 100,
      "Cassiopeia": 100,
      "Varus": 100,
      "Renata Glasc": 100,
      "Sivir": 100,
      "Katarina": 100,
      "Kalista": 100,
      "Miss Fortune": 100,
      "Kog'Maw": 100,
      "Corki": 100,
      "Tristana": 100,
      "Lucian": 83.33,
      "Karthus": 66.67,
      "Ezreal": 66.67,
      "Vayne": 66.67,
      "Jhin": 61.54,
      "Draven": 60,
      "Jinx": 58.33,
      "Caitlyn": 54.55,
      "Samira": 50,
      "Aphelios": 50,
      "Twitch": 50,
      "Senna": 50,
      "Nilah": 50,
      "Swain": 50,
      "Mel": 50,
      "Aurelion Sol": 50,
      "Ashe": 45.45,
      "Yunara": 33.33,
      "Vladimir": 33.33,
      "Kai'Sa": 25,
      "Xayah": 25,
      "Yasuo": 20,
      "Hwei": 0,
      "Smolder": 0
    },
    "support": {
      "Seraphine": 90,
      "Tahm Kench": 85.71,
      "Sylas": 85.71,
      "Rakan": 80,
      "Shaco": 80,
      "Lulu": 79.31,
      "Rell": 75,
      "Blitzcrank": 75,
      "Leona": 73.33,
      "Nami": 72.22,
      "Anivia": 71.43,
      "Karma": 70.37,
      "Milio": 68,
      "Lux": 66.67,
      "Yuumi": 66.67,
      "Bard": 66.67,
      "Janna": 61.54,
      "Soraka": 61.29,
      "Renata Glasc": 60,
      "Poppy": 60,
      "Zyra": 57.14,
      "Morgana": 56.25,
      "Brand": 53.33,
      "Braum": 53.33,
      "Nautilus": 51.85,
      "Neeko": 50,
      "Taric": 50,
      "Maokai": 50,
      "Pantheon": 50,
      "Pyke": 50,
      "Ashe": 50,
      "Mel": 50,
      "Xerath": 50,
      "Senna": 46.67,
      "Vel'Koz": 42.86,
      "Thresh": 42.31,
      "Alistar": 40,
      "Sona": 36.36,
      "Zilean": 33.33,
      "Swain": 30
    }
  }
}
