{
  "id": "Hwei",
  "name": "Hwei",
  "positions": [
    "Mid",
    "Bottom"
  ],
  "matchups": {
    "top": {
      "Cassiopeia": 80,
      "Vayne": 71.43,
      "Heimerdinger": 68.75,
      "Sion": 66.67,
      "Olaf": 66.67,
      "Aurora": 66.67,
      "Dr. Mundo": 66.67,
      "Camille": 64.29,
      "Teemo": 63.64,
      "Pantheon": 62.5,
      "Sylas": 60,
      "Akali": 60,
      "Darius": 56.52,
      "Shen": 55,
      "Anivia": 54.55,
      "Malphite": 53.33,
      "Jax": 52.94,
      "Tryndamere": 50,
      "Irelia": 50,
      "Quinn": 50,
      "Ryze": 50,
      "Gwen": 50,
      "Riven": 50,
      "Sett": 47.06,
      "Kayle": 46.67,
      "Yasuo": 46.15,
      "Ornn": 45.45,
      "Garen": 44.74,
      "Vladimir": 44.44,
      "Varus": 43.75,
      "Renekton": 43.48,
      "Gragas": 42.86,
      "Ambessa": 42.86,
      "K'Sante": 41.67,
      "Yorick": 41.67,
      "Mordekaiser": 40.91,
      "Singed": 40,
      "Jayce": 37.5,
      "Kled": 37.5,
      "Rumble": 36.36,
      "Gangplank": 35.71,
      "Illaoi": 33.33,
      "Nasus": 33.33,
      "Gnar": 33.33,
      "Kennen": 30,
      "Cho'Gath": 28.57,
      "Yone": 28.57,
      "Volibear": 26.67,
      "Fiora": 25,
      "Aatrox": 23.81,
      "Zaahen": 22.22,
      "Poppy": 22.22,
      "Urgot": 20,
      "Tahm Kench": 14.29
    },
    "jungle": {
      "Udyr": 100,
      "Rammus": 100,
      "Master Yi": 100,
      "Viego": 0,
      "Zac": 0
    },
    "middle": {
      "Katarina": 55.4,
      "Ziggs": 55.32,
      "Zoe": 53.86,
      "Naafiri": 53.52,
      "Xerath": 52.9,
      "Akshan": 52.62,
      "Lux": 52.55,
      "Cassiopeia": 52.41,
      "Fizz": 52.2,
      "Syndra": 52.17,
      "Ekko": 51.71,
      "Yasuo": 51.68,
      "Aurelion Sol": 51.64,
      "Akali": 51.39,
      "Veigar": 51.37,
      "Anivia": 51.33,
      "Kassadin": 51.16,
      "Annie": 50.72,
      "Aurora": 50.64,
      "Ahri": 50.5,
      "Brand": 50.43,
      "Diana": 50.07,
      "Twisted Fate": 50.05,
      "Vex": 50,
      "Malzahar": 49.82,
      "Zed": 49.68,
      "LeBlanc": 49.62,
      "Vel'Koz": 49.48,
      "Irelia": 49.44,
      "Talon": 48.35,
      "Yone": 48.34,
      "Lissandra": 48.34,
      "Viktor": 48.27,
      "Sylas": 47.95,
      "Qiyana": 47.93,
      "Sion": 47.92,
      "Taliyah": 47.76,
      "Vladimir": 47.31,
      "Orianna": 46.84,
      "Swain": 46.44,
      "Mel": 46.01,
      "Ryze": 44.7,
      "Azir": 41.98,
      "Galio": 40.83
    },
    "adc": {
      "Seraphine": 62.07,
      "Karthus": 61.11,
      "Mel": 57.14,
      "Ziggs": 56.94,
      "Xayah": 56.03,
      "Lucian": 52.87,
      "Vayne": 51.3,
      "Jhin": 51.16,
      "Twitch": 51.13,
      "Varus": 51.11,
      "Kog'Maw": 50.82,
      "Ashe": 50.68,
      "Smolder": 50.19,
      "Jinx": 50,
      "Aurelion Sol": 48.72,
      "Brand": 48.57,
      "Kai'Sa": 48.13,
      "Samira": 47.76,
      "Yunara": 47.66,
      "Lux": 47.5,
      "Ezreal": 47.36,
      "Draven": 46.82,
      "Senna": 46.75,
      "Aphelios": 46.73,
      "Caitlyn": 46.55,
      "Sivir": 45.58,
      "Tristana": 45.22,
      "Zeri": 44.9,
      "Nilah": 44.44,
      "Kalista": 44.44,
      "Corki": 44.17,
      "Miss Fortune": 43.55,
      "Veigar": 43.4,
      "Swain": 40,
      "Yasuo": 34.88
    },
    "support": {
      "Janna": 62.96,
      "Blitzcrank": 60.14,
      "Mel": 59,
      "Xerath": 57.72,
      "Taric": 56.67,
      "Vel'Koz": 55.84,
      "Nami": 54.95,
      "Karma": 54.8,
      "Rakan": 54.39,
      "Pyke": 54.3,
      "Milio": 54.05,
      "Nautilus": 53.48,
      "Lux": 53.11,
      "Neeko": 52.46,
      "Lulu": 52.07,
      "Rell": 51.76,
      "Morgana": 51.22,
      "Yuumi": 50.34,
      "Braum": 50.33,
      "Sona": 50,
      "Poppy": 50,
      "Soraka": 49.68,
      "Seraphine": 49.47,
      "Zyra": 49.43,
      "Thresh": 49.21,
      "Anivia": 48.89,
      "Swain": 48.65,
      "Tahm Kench": 48.39,
      "Zilean": 48.1,
      "Bard": 47.49,
      "Elise": 47.22,
      "Brand": 47.19,
      "Leona": 46.56,
      "Maokai": 45.1,
      "Senna": 43.36,
      "Pantheon": 41.86,
      "Shaco": 39.02,
      "Alistar": 38.52
    }
  }
}
